xplan_gui/app.py
xplan_gui/crud.py
xplan_gui/db.py
xplan_gui/form.py
xplan_gui/main.py
xplan_gui/map.py
xplan_gui/model_ui.py
xplan_gui/settings.py
xplan_gui/pygeoapi/provider.py
xplan_gui-0.1.0.dist-info/licenses/LICENSE.md
xplan_gui-0.1.0.dist-info/METADATA
xplan_gui-0.1.0.dist-info/WHEEL
xplan_gui-0.1.0.dist-info/top_level.txt
xplan_gui-0.1.0.dist-info/RECORD
