Metadata-Version: 2.4
Name: xplan-gui
Version: 0.1.0
Author-email: Tobias Kraft <tobias.kraft@gv.hamburg.de>
License-Expression: EUPL-1.2
Requires-Python: >=3.10
License-File: LICENSE.md
Requires-Dist: folium<0.17,>=0.16
Requires-Dist: pydantic-settings<3.0,>=2.0
Requires-Dist: build<2,>=1.3.0
Requires-Dist: setuptools
Requires-Dist: wheel<0.46,>=0.45.1
Dynamic: license-file
